leetpie/__init__.py
leetpie/cli.py
leetpie/helper.py
leetpie/problems.py
leetpie/utils.py
leetpie-0.1.0.dist-info/entry_points.txt
leetpie-0.1.0.dist-info/LICENSE
leetpie-0.1.0.dist-info/METADATA
leetpie-0.1.0.dist-info/WHEEL
leetpie-0.1.0.dist-info/RECORD
