Metadata-Version: 2.1
Name: leetpie
Version: 0.1.0
Summary: LeetPie: Easily manage your LeetCode solutions.
Author: Logan
Author-email: 146642263+logan2d5@users.noreply.github.com
Requires-Python: >=3.10,<4.0
Classifier: Programming Language :: Python :: 3
Classifier: Programming Language :: Python :: 3.10
Classifier: Programming Language :: Python :: 3.11
Classifier: Programming Language :: Python :: 3.12
Requires-Dist: typer[all] (>=0.12.3,<0.13.0)
